scan_utils/__init__.py
scan_utils/main.py
scan_utils/pkg/__init__.py
scan_utils/pkg/framework/__init__.py
scan_utils/pkg/framework/exception.py
scan_utils/pkg/framework/log_utility.py
scan_utils/pkg/utils/__init__.py
scan_utils/pkg/utils/database.py
scan_utils/pkg/utils/diff.py
scan_utils/pkg/utils/kafka_utils.py
scan_utils/pkg/utils/process.py
scan_utils/pkg/utils/shell.py
scan_utils/pkg/utils/snmp.py
scan_utils/pkg/utils/ssh.py
scan_utils/pkg/utils/utility.py
scan_utils/pkg/utils/wmi.py
scan_utils/pkg/vars/__init__.py
scan_utils/pkg/vars/global_var.py
scan_utils-0.0.15.dist-info/licenses/LICENSE
scan_utils-0.0.15.dist-info/METADATA
scan_utils-0.0.15.dist-info/WHEEL
scan_utils-0.0.15.dist-info/top_level.txt
scan_utils-0.0.15.dist-info/RECORD
