Metadata-Version: 2.4
Name: scan-utils
Version: 0.0.15
Summary: uitls for scan service
Author-email: LiamLea <liweixiliang@gmail.com>
License: MIT License
Classifier: Programming Language :: Python :: 3
Classifier: License :: OSI Approved :: MIT License
Classifier: Operating System :: OS Independent
Requires-Python: >=3.6
License-File: LICENSE
Dynamic: license-file
